num_word_converter/__init__.py
num_word_converter/consts.py
num_word_converter/errors.py
num_word_converter/num2word.py
num_word_converter/word2num.py
tests/__init__.py
tests/num2word_tests/__init__.py
tests/num2word_tests/tests.py
tests/word2num_tests/__init__.py
tests/word2num_tests/tests.py
num_word_converter-1.0.8.dist-info/METADATA
num_word_converter-1.0.8.dist-info/WHEEL
num_word_converter-1.0.8.dist-info/top_level.txt
num_word_converter-1.0.8.dist-info/RECORD
