Metadata-Version: 2.1
Name: num-word-converter
Version: 1.0.8
Summary: A package to convert numbers to words and vice-versa
Author: Vladyslav Lazoryk
Author-email: lazorkinv@gmail.com
Classifier: License :: OSI Approved :: Python Software Foundation License
Classifier: Programming Language :: Python
Classifier: Programming Language :: Python :: 3
Classifier: Programming Language :: Python :: 3.12
